gpry/CobayaSampler.yaml
gpry/__init__.py
gpry/acquisition_functions.py
gpry/cobaya.py
gpry/convergence.py
gpry/gp_acquisition.py
gpry/gpr.py
gpry/io.py
gpry/kernels.py
gpry/mc.py
gpry/mpi.py
gpry/plots.py
gpry/preprocessing.py
gpry/progress.py
gpry/proposal.py
gpry/run.py
gpry/svm.py
gpry/tools.py
gpry-2.0.1.dist-info/LICENSE
gpry-2.0.1.dist-info/METADATA
gpry-2.0.1.dist-info/WHEEL
gpry-2.0.1.dist-info/top_level.txt
gpry-2.0.1.dist-info/RECORD
