Metadata-Version: 2.1
Name: gpry
Version: 2.0.1
Summary: A package for fast bayesian inference of expensive Likelihoods
Home-page: https://github.com/jonaselgammal/GPry
Author: Jonas El Gammal, Jesus Torrado, Nils Schoeneberg and Christian Fidler
Author-email: jonas.el.gammal@rwth-aachen.de
License: LGPL
Project-URL: Documentation, https://gpry.readthedocs.io
Project-URL: Source, https://github.com/jonaselgammal/GPry
Keywords: inference,gaussianprocesses,sampling,cosmology
Classifier: Development Status :: 4 - Beta
Classifier: Operating System :: OS Independent
Classifier: Environment :: Console
Classifier: Intended Audience :: Science/Research
Classifier: Topic :: Scientific/Engineering :: Astronomy
Classifier: License :: OSI Approved :: GNU Lesser General Public License v3 (LGPLv3)
Classifier: Programming Language :: Python :: 3.8
Classifier: Programming Language :: Python :: 3.9
License-File: LICENSE
Requires-Dist: cobaya (>=3.2.2)
Requires-Dist: scikit-learn
Requires-Dist: dill
Requires-Dist: mpi4py
